rockpaperscissors2333/__init__.py
rockpaperscissors2333/__main__.py
rockpaperscissors2333/cli.py
rockpaperscissors2333/game.py
rockpaperscissors2333-1.1.3.dist-info/LICENSE
rockpaperscissors2333-1.1.3.dist-info/METADATA
rockpaperscissors2333-1.1.3.dist-info/WHEEL
rockpaperscissors2333-1.1.3.dist-info/entry_points.txt
rockpaperscissors2333-1.1.3.dist-info/top_level.txt
rockpaperscissors2333-1.1.3.dist-info/RECORD
