Metadata-Version: 2.1
Name: rockpaperscissors2333
Version: 1.1.3
Summary: A simple Rock, Paper, Scissors game.
Author-email: Zijie Zhao <zz3589@nyu.edu>
License: GNU GENERAL PUBLIC LICENSE
Project-URL: Homepage, https://github.com/software-students-spring2024/pysong
Project-URL: Repository, https://github.com/software-students-spring2024/pysong.git
Project-URL: Bug Tracker, https://github.com/software-students-spring2024/pysong/issues
Keywords: python,package,game,rock-paper-scissors
Classifier: Programming Language :: Python :: 3
Classifier: Intended Audience :: Education
Classifier: License :: OSI Approved :: GNU General Public License v3 (GPLv3)
Classifier: Operating System :: OS Independent
Requires-Python: >=3.7
License-File: LICENSE
Provides-Extra: dev
Requires-Dist: pytest ; extra == 'dev'
